src/__init__.py
src/server.py
taskify_mcp_server-0.1.3.dist-info/METADATA
taskify_mcp_server-0.1.3.dist-info/WHEEL
taskify_mcp_server-0.1.3.dist-info/entry_points.txt
taskify_mcp_server-0.1.3.dist-info/RECORD
