Metadata-Version: 2.3
Name: taskify-mcp-server
Version: 0.1.3
Summary: 
Author: GeeseDream
Author-email: GeeseDream@aliyun.com
Requires-Python: >=3.12
Classifier: Programming Language :: Python :: 3
Classifier: Programming Language :: Python :: 3.12
Classifier: Programming Language :: Python :: 3.13
Requires-Dist: mcp[cli] (>=1.10.1,<2.0.0)
